nv_ingest_client/__init__.py
nv_ingest_client/nv_ingest_cli.py
nv_ingest_client/cli/__init__.py
nv_ingest_client/cli/util/__init__.py
nv_ingest_client/cli/util/click.py
nv_ingest_client/cli/util/processing.py
nv_ingest_client/cli/util/system.py
nv_ingest_client/cli/util/tasks.py
nv_ingest_client/client/__init__.py
nv_ingest_client/client/client.py
nv_ingest_client/client/interface.py
nv_ingest_client/client/util/processing.py
nv_ingest_client/primitives/__init__.py
nv_ingest_client/primitives/exceptions.py
nv_ingest_client/primitives/jobs/__init__.py
nv_ingest_client/primitives/jobs/job_spec.py
nv_ingest_client/primitives/jobs/job_state.py
nv_ingest_client/primitives/tasks/__init__.py
nv_ingest_client/primitives/tasks/audio_extraction.py
nv_ingest_client/primitives/tasks/caption.py
nv_ingest_client/primitives/tasks/chart_extraction.py
nv_ingest_client/primitives/tasks/dedup.py
nv_ingest_client/primitives/tasks/embed.py
nv_ingest_client/primitives/tasks/extract.py
nv_ingest_client/primitives/tasks/filter.py
nv_ingest_client/primitives/tasks/infographic_extraction.py
nv_ingest_client/primitives/tasks/split.py
nv_ingest_client/primitives/tasks/store.py
nv_ingest_client/primitives/tasks/table_extraction.py
nv_ingest_client/primitives/tasks/task_base.py
nv_ingest_client/primitives/tasks/task_factory.py
nv_ingest_client/primitives/tasks/transform.py
nv_ingest_client/primitives/tasks/vdb_upload.py
nv_ingest_client/util/__init__.py
nv_ingest_client/util/dataset.py
nv_ingest_client/util/milvus.py
nv_ingest_client/util/process_json_files.py
nv_ingest_client/util/processing.py
nv_ingest_client/util/system.py
nv_ingest_client/util/transport.py
nv_ingest_client/util/util.py
nv_ingest_client/util/zipkin.py
nv_ingest_client/util/file_processing/__init__.py
nv_ingest_client/util/file_processing/extract.py
nv_ingest_client/util/vdb/__init__.py
nv_ingest_client/util/vdb/adt_vdb.py
nv_ingest_client/util/vdb/milvus.py
nv_ingest_client/util/vdb/opensearch.py
nv_ingest_client-25.9.0.dist-info/licenses/LICENSE
nv_ingest_client-25.9.0.dist-info/METADATA
nv_ingest_client-25.9.0.dist-info/WHEEL
nv_ingest_client-25.9.0.dist-info/entry_points.txt
nv_ingest_client-25.9.0.dist-info/top_level.txt
nv_ingest_client-25.9.0.dist-info/RECORD
