Metadata-Version: 2.4
Name: nv-ingest-client
Version: 25.9.0
Summary: Python client for the nv-ingest service
Author-email: Jeremy Dyer <jdyer@nvidia.com>
License:                                  Apache License
Project-URL: homepage, https://github.com/NVIDIA/nv-ingest
Project-URL: repository, https://github.com/NVIDIA/nv-ingest
Project-URL: documentation, https://docs.nvidia.com/nv-ingest
Classifier: Programming Language :: Python :: 3.11
Classifier: Operating System :: OS Independent
Requires-Python: >=3.11
License-File: LICENSE
Requires-Dist: build>=1.2.2
Requires-Dist: charset-normalizer>=3.4.1
Requires-Dist: click>=8.1.8
Requires-Dist: fsspec>=2025.2.0
Requires-Dist: httpx>=0.28.1
Requires-Dist: llama-index-embeddings-nvidia==0.1.5
Requires-Dist: nv-ingest-api==25.9.0
Requires-Dist: pydantic>2.0.0
Requires-Dist: pydantic-settings>2.0.0
Requires-Dist: requests>=2.28.2
Requires-Dist: setuptools>=78.1.1
Requires-Dist: tqdm>=4.67.1
Provides-Extra: milvus
Requires-Dist: pymilvus==2.5.10; extra == "milvus"
Requires-Dist: pymilvus[bulk_writer,model]; extra == "milvus"
Provides-Extra: minio
Requires-Dist: minio>=7.2.15; extra == "minio"
Dynamic: license-file
